{
  "lookup": {
    "rules": {
      "[{\"prev_action\": {\"action_name\": \"action_listen\"}, \"user\": {\"intent\": \"chitchat\"}}]": "action_handle_chitchat",
      "[{\"prev_action\": {\"action_name\": \"action_listen\"}, \"user\": {\"intent\": \"chitchat\"}}, {\"prev_action\": {\"action_name\": \"action_handle_chitchat\"}, \"user\": {\"intent\": \"chitchat\"}}]": "action_listen",
      "[{\"prev_action\": {\"action_name\": \"action_listen\"}, \"user\": {\"intent\": \"consultar_evento\"}}]": "action_consultar_evento",
      "[{\"prev_action\": {\"action_name\": \"action_listen\"}, \"user\": {\"intent\": \"consultar_evento\"}}, {\"prev_action\": {\"action_name\": \"action_consultar_evento\"}, \"user\": {\"intent\": \"consultar_evento\"}}]": "action_listen",
      "[{\"prev_action\": {\"action_name\": \"action_listen\"}, \"user\": {\"intent\": \"bot_challenge\"}}]": "utter_iamabot",
      "[{\"prev_action\": {\"action_name\": \"action_listen\"}, \"user\": {\"intent\": \"bot_challenge\"}}, {\"prev_action\": {\"action_name\": \"utter_iamabot\"}, \"user\": {\"intent\": \"bot_challenge\"}}]": "action_listen",
      "[{\"prev_action\": {\"action_name\": \"action_listen\"}, \"user\": {\"intent\": \"goodbye\"}}]": "utter_goodbye",
      "[{\"prev_action\": {\"action_name\": \"action_listen\"}, \"user\": {\"intent\": \"goodbye\"}}, {\"prev_action\": {\"action_name\": \"utter_goodbye\"}, \"user\": {\"intent\": \"goodbye\"}}]": "action_listen",
      "[{\"prev_action\": {\"action_name\": \"action_listen\"}, \"user\": {\"intent\": \"crear_evento\"}}]": "action_validar_y_crear_evento",
      "[{\"prev_action\": {\"action_name\": \"action_listen\"}, \"user\": {\"intent\": \"crear_evento\"}}, {\"prev_action\": {\"action_name\": \"action_validar_y_crear_evento\"}, \"user\": {\"intent\": \"crear_evento\"}}]": "action_listen"
    },
    "rule_only_slots": [],
    "rule_only_loops": [],
    "rules_for_loop_unhappy_path": {},
    "rules_not_in_stories": [
      "[{\"prev_action\": {\"action_name\": \"action_listen\"}, \"user\": {\"intent\": \"goodbye\"}}]",
      "predicting default action with intent session_start",
      "[{\"prev_action\": {\"action_name\": \"action_listen\"}, \"user\": {\"intent\": \"chitchat\"}}, {\"prev_action\": {\"action_name\": \"action_handle_chitchat\"}, \"user\": {\"intent\": \"chitchat\"}}]",
      "[{\"prev_action\": {\"action_name\": \"action_listen\"}, \"user\": {\"intent\": \"bot_challenge\"}}]",
      "[{\"prev_action\": {\"action_name\": \"action_listen\"}, \"user\": {\"intent\": \"consultar_evento\"}}]",
      "[{\"prev_action\": {\"action_name\": \"action_listen\"}, \"user\": {\"intent\": \"consultar_evento\"}}, {\"prev_action\": {\"action_name\": \"action_consultar_evento\"}, \"user\": {\"intent\": \"consultar_evento\"}}]",
      "[{\"prev_action\": {\"action_name\": \"action_listen\"}, \"user\": {\"intent\": \"goodbye\"}}, {\"prev_action\": {\"action_name\": \"utter_goodbye\"}, \"user\": {\"intent\": \"goodbye\"}}]",
      "[{\"prev_action\": {\"action_name\": \"action_listen\"}, \"user\": {\"intent\": \"crear_evento\"}}]",
      "predicting default action with intent back",
      "predicting default action with intent restart",
      "[{\"prev_action\": {\"action_name\": \"action_listen\"}, \"user\": {\"intent\": \"chitchat\"}}]",
      "[{\"prev_action\": {\"action_name\": \"action_listen\"}, \"user\": {\"intent\": \"bot_challenge\"}}, {\"prev_action\": {\"action_name\": \"utter_iamabot\"}, \"user\": {\"intent\": \"bot_challenge\"}}]",
      "[{\"prev_action\": {\"action_name\": \"action_listen\"}, \"user\": {\"intent\": \"crear_evento\"}}, {\"prev_action\": {\"action_name\": \"action_validar_y_crear_evento\"}, \"user\": {\"intent\": \"crear_evento\"}}]"
    ]
  }
}